CHANGES.rst
sentry_msg/__init__.py
sentry_wrapper/__init__.py
sentry_wrapper-3.0.1.dist-info/METADATA
sentry_wrapper-3.0.1.dist-info/WHEEL
sentry_wrapper-3.0.1.dist-info/entry_points.txt
sentry_wrapper-3.0.1.dist-info/RECORD
