Metadata-Version: 2.1
Name: sentry-wrapper
Version: 3.0.1
Summary: Forward exceptions raised by a setuptools entrypoint to sentry
Home-page: https://github.com/scaleway/sentry-wrapper
License: WTFPL
Author: Julien Castets
Author-email: castets.j@gmail.com
Requires-Python: >=3.6,<4.0
Classifier: Development Status :: 4 - Beta
Classifier: Intended Audience :: Developers
Classifier: License :: OSI Approved :: BSD License
Classifier: License :: Other/Proprietary License
Classifier: Operating System :: MacOS
Classifier: Operating System :: POSIX
Classifier: Operating System :: Unix
Classifier: Programming Language :: Python
Classifier: Programming Language :: Python :: 3
Classifier: Programming Language :: Python :: 3.6
Classifier: Programming Language :: Python :: 3.7
Classifier: Programming Language :: Python :: 3.8
Classifier: Programming Language :: Python :: 3.9
Classifier: Programming Language :: Python :: 3.10
Classifier: Programming Language :: Python :: 3.11
Classifier: Programming Language :: Python :: 3.12
Classifier: Topic :: Internet
Classifier: Topic :: Software Development :: Libraries :: Python Modules
Classifier: Topic :: System :: Distributed Computing
Requires-Dist: sentry-sdk (>=2.18.0,<3.0.0)
Project-URL: Repository, https://github.com/scaleway/sentry-wrapper
